setup.py
satori_raspberry/__init__.py
satori_raspberry/controller.py
satori_raspberry.egg-info/PKG-INFO
satori_raspberry.egg-info/SOURCES.txt
satori_raspberry.egg-info/dependency_links.txt
satori_raspberry.egg-info/requires.txt
satori_raspberry.egg-info/top_level.txt
satori_raspberry.egg-info/zip-safe
satori_raspberry/skills/__init__.py
satori_raspberry/skills/adc.py
satori_raspberry/skills/barometer.py
satori_raspberry/skills/base.py
satori_raspberry/skills/button.py
satori_raspberry/skills/general.py
satori_raspberry/skills/humiture.py
satori_raspberry/skills/ir_controller.py
satori_raspberry/skills/ir_obstacle.py
satori_raspberry/skills/lcd.py
satori_raspberry/skills/led.py
satori_raspberry/skills/photoresistor.py
satori_raspberry/skills/temperature.py